ladybug_grasshopper/__init__.py
ladybug_grasshopper/src/LB Adaptive Chart.py
ladybug_grasshopper/src/LB Adaptive Comfort Parameters.py
ladybug_grasshopper/src/LB Adaptive Comfort.py
ladybug_grasshopper/src/LB Analysis Period.py
ladybug_grasshopper/src/LB Ankle Draft.py
ladybug_grasshopper/src/LB Apply Analysis Period.py
ladybug_grasshopper/src/LB Apply Conditional Statement.py
ladybug_grasshopper/src/LB Apply Pattern.py
ladybug_grasshopper/src/LB Area Aggregate.py
ladybug_grasshopper/src/LB Area Normalize.py
ladybug_grasshopper/src/LB Arithmetic Operation.py
ladybug_grasshopper/src/LB Benefit Sky Matrix.py
ladybug_grasshopper/src/LB Calculate HOY.py
ladybug_grasshopper/src/LB Capture View.py
ladybug_grasshopper/src/LB Clothing by Temperature.py
ladybug_grasshopper/src/LB Color Range.py
ladybug_grasshopper/src/LB Comfort Statistics.py
ladybug_grasshopper/src/LB Compass.py
ladybug_grasshopper/src/LB Construct Data Type.py
ladybug_grasshopper/src/LB Construct Data.py
ladybug_grasshopper/src/LB Construct Header.py
ladybug_grasshopper/src/LB Construct Location.py
ladybug_grasshopper/src/LB Construct Matrix.py
ladybug_grasshopper/src/LB Convert to Timestep.py
ladybug_grasshopper/src/LB Create Legend.py
ladybug_grasshopper/src/LB Cumulative Sky Matrix.py
ladybug_grasshopper/src/LB Data DateTimes.py
ladybug_grasshopper/src/LB Day Solar Information.py
ladybug_grasshopper/src/LB Deconstruct Data.py
ladybug_grasshopper/src/LB Deconstruct Design Day.py
ladybug_grasshopper/src/LB Deconstruct Header.py
ladybug_grasshopper/src/LB Deconstruct Location.py
ladybug_grasshopper/src/LB Deconstruct Matrix.py
ladybug_grasshopper/src/LB Deconstruct VisualizationSet.py
ladybug_grasshopper/src/LB Degree Days.py
ladybug_grasshopper/src/LB Direct Sun Hours.py
ladybug_grasshopper/src/LB Directional Solar Irradiance.py
ladybug_grasshopper/src/LB Download Weather.py
ladybug_grasshopper/src/LB Dump Data.py
ladybug_grasshopper/src/LB Dump VisualizationSet.py
ladybug_grasshopper-1.69.2.dist-info/licenses/LICENSE
ladybug_grasshopper-1.69.2.dist-info/METADATA
ladybug_grasshopper-1.69.2.dist-info/WHEEL
ladybug_grasshopper-1.69.2.dist-info/top_level.txt
ladybug_grasshopper-1.69.2.dist-info/RECORD
