Metadata-Version: 2.4
Name: ladybug-grasshopper
Version: 1.69.2
Summary: Ladybug plugin for Grasshopper.
Home-page: https://github.com/ladybug-tools/ladybug-grasshopper
Author: Ladybug Tools
Author-email: info@ladybug.tools
License: AGPL-3.0
Classifier: Programming Language :: Python :: 2.7
Classifier: Programming Language :: Python :: Implementation :: IronPython
Classifier: Operating System :: OS Independent
License-File: LICENSE
Dynamic: author
Dynamic: author-email
Dynamic: classifier
Dynamic: description
Dynamic: description-content-type
Dynamic: home-page
Dynamic: license
Dynamic: license-file
Dynamic: summary
